README.md
setup.py
globomap_loader_api_client/__init__.py
globomap_loader_api_client/auth.py
globomap_loader_api_client/base.py
globomap_loader_api_client/exceptions.py
globomap_loader_api_client/settings.py
globomap_loader_api_client/update.py
globomap_loader_api_client.egg-info/PKG-INFO
globomap_loader_api_client.egg-info/SOURCES.txt
globomap_loader_api_client.egg-info/dependency_links.txt
globomap_loader_api_client.egg-info/requires.txt
globomap_loader_api_client.egg-info/top_level.txt