Metadata-Version: 1.0
Name: globomap-loader-api-client
Version: 0.0.11
Summary: Client to GloboMAP Loader API
Home-page: https://github.com/globocom/globomap-loader-api-client
Author: Ederson Brilhante
Author-email: ederson.brilhante@corp.globo.com
License: UNKNOWN
Platform: UNKNOWN
